{
  "$schema_version": "1.0.0",
  "description": "Authoritative pure-data blocks extracted from AUDIT.md per E004. This file is the normative source of truth for the 11 closed-set / ordered-list / regex-pattern schemas that AUDIT.md's rules constrain. AUDIT.md retains explanatory prose at each original location and points here for the actual values. F007 (schema-contract-stability fixture) validates each block's structural invariants + cross-block consistency against this file.",
  "generated_at": "2026-04-21",
  "source": "AUDIT.md pre-E004 fingerprint sha256:8523ec7815c83f44c2abab1f80fc8ad229ca4baa63b6126f60220a9c26db4556",
  "e004_ledger": "evals/proposal-history/APPLIED-2026-04-21-E004.md",

  "blocks": {

    "type3_mapping": {
      "_comment": "§1 'The 12 canonical TYPE3 codes'. Every item ID is AUD-YYYY-MM-DD-<TYPE3>-<NNNN>. The 12 three-letter codes below are the COMPLETE closed set — no synonyms, no invention. Forbidden codes (always fail conformance): QA→QLT, DX→DEV, DOCS→DOC, PERF→PRF, ARCH→ARC. TYPE3 must be exactly 3 characters.",
      "bijection": {
        "SEC": "security",
        "PRF": "performance",
        "REL": "reliability",
        "QLT": "quality",
        "ARC": "architecture",
        "DEV": "dx",
        "DOC": "docs",
        "INF": "infrastructure",
        "FEA": "feature",
        "IDA": "idea",
        "REF": "refactor",
        "TST": "test"
      },
      "forbidden_aliases": {
        "QA": "QLT",
        "DX": "DEV",
        "DOCS": "DOC",
        "PERF": "PRF",
        "ARCH": "ARC"
      },
      "expected_row_count": 12
    },

    "status_state_machine": {
      "_comment": "§STATUS STATE MACHINE. 7-element closed set of status names + allowed transitions. Terminal statuses (DONE, WONT_DO, REJECTED) appear in state but have no outgoing edges. Every transition appends to history[], transitions.jsonl, and CHANGELOG.md. Only APPROVED+AGENT is execute-eligible.",
      "statuses": [
        "PROPOSED",
        "APPROVED",
        "IN_PROGRESS",
        "DONE",
        "DEFERRED",
        "WONT_DO",
        "REJECTED"
      ],
      "terminal_statuses": ["DONE", "WONT_DO", "REJECTED"],
      "transitions": [
        ["PROPOSED", "APPROVED"],
        ["PROPOSED", "REJECTED"],
        ["PROPOSED", "DEFERRED"],
        ["APPROVED", "IN_PROGRESS"],
        ["APPROVED", "DEFERRED"],
        ["APPROVED", "WONT_DO"],
        ["IN_PROGRESS", "DONE"],
        ["IN_PROGRESS", "DEFERRED"],
        ["DEFERRED", "APPROVED"],
        ["DEFERRED", "WONT_DO"]
      ]
    },

    "moscow_priorities": {
      "_comment": "§Definitions §MoSCoW. Ordered (priority-descending) closed set of 4 values. MUST blocks release; WONT terminalizes to wont-do.json.",
      "ordered": ["MUST", "SHOULD", "COULD", "WONT"],
      "semantics": {
        "MUST":   "Security-critical, data loss, broken builds, compliance gaps. Block release.",
        "SHOULD": "High-value perf / reliability / maintainability. Address this cycle.",
        "COULD":  "Nice-to-have. Backlog candidate.",
        "WONT":   "Out of scope or explicitly declined. Terminalize to wont-do.json."
      }
    },

    "scanner_manifest": {
      "_comment": "§Scanner manifest (MANDATORY in generated_runs[N].scanners). 8-element ordered closed set. Consolidate mode MAY emit [\"consolidate\"] instead. Any other subset is non-conformant.",
      "ordered": [
        "security",
        "performance",
        "reliability",
        "quality",
        "architecture",
        "dx",
        "docs",
        "ideas"
      ],
      "consolidate_alternative": ["consolidate"]
    },

    "evidence_redaction_patterns": {
      "_comment": "§EVIDENCE REDACTION. 8 regex→label pairs applied to every evidence[].snippet and finding text BEFORE any persistence. Patterns target secret VALUES, not structural keywords (YAML key names, shell var refs, function params, schema keywords). Extension seam: config.yaml → redaction.extra_patterns.",
      "patterns": [
        {"pattern": "AKIA[0-9A-Z]{16}",                                                                          "label": "[REDACTED:aws-key]"},
        {"pattern": "(?<![A-Za-z0-9/+=])[A-Za-z0-9/+=]{40}(?![A-Za-z0-9/+=])",                                   "label": "[REDACTED:possible-aws-secret]"},
        {"pattern": "(?i)(api[_-]?key|token|secret)\\s*[:=]\\s*['\"]?[A-Za-z0-9_\\-]{20,}['\"]?",                "label": "[REDACTED:token]"},
        {"pattern": "sk_live_[0-9a-zA-Z]{24,}",                                                                  "label": "[REDACTED:stripe-key]"},
        {"pattern": "xox[abprs]-[A-Za-z0-9-]{10,}",                                                              "label": "[REDACTED:slack-token]"},
        {"pattern": "gh[pousr]_[A-Za-z0-9]{36,}",                                                                "label": "[REDACTED:github-token]"},
        {"pattern": "-----BEGIN [A-Z ]*PRIVATE KEY-----[\\s\\S]*?-----END [A-Z ]*PRIVATE KEY-----",              "label": "[REDACTED:private-key]"},
        {"pattern": "eyJ[A-Za-z0-9_-]+\\.eyJ[A-Za-z0-9_-]+\\.[A-Za-z0-9_-]+",                                    "label": "[REDACTED:jwt]"}
      ],
      "forbidden_labels": [
        "[REDACTED:PASSWORD]",
        "[REDACTED:SECRET]",
        "[REDACTED:API_KEY]",
        "[REDACTED:CREDENTIAL]",
        "[REDACTED:KEY]",
        "[REDACTED:input]",
        "[REDACTED:env]",
        "[REDACTED]"
      ]
    },

    "details_schema_by_level": {
      "_comment": "§ITEM SCHEMA 'details schema by level'. The details object schema VARIES BY LEVEL. Over-filling is a hard violation equal in severity to under-filling. Set equality: set(it.details.keys()) == REQUIRED ∪ (allowed_subset_used) AND keys ∩ FORBIDDEN == ∅.",
      "epic": {
        "required":  ["what", "why"],
        "allowed":   [],
        "forbidden": ["who", "when", "where", "how", "cost", "constraints", "5m"]
      },
      "story": {
        "required":  ["what", "why"],
        "allowed":   ["who", "when", "where"],
        "forbidden": ["how", "cost", "constraints", "5m"]
      },
      "task": {
        "required":  ["what", "why", "who", "when", "where", "how", "cost", "constraints", "5m"],
        "allowed":   [],
        "forbidden": []
      }
    },

    "counts_closed_sets": {
      "_comment": "§OUTPUT CONTRACT 'Derivation rule'. counts.* are state snapshots (totals over live items[], cumulative across all runs). Closed-set counts.* keys: EXACTLY total, by_level, by_moscow, by_assignee, by_status. Flow metrics (new/merged/deduped) live on generated_runs[N], NOT counts. Emit every key even when zero.",
      "top_level_keys": ["total", "by_level", "by_moscow", "by_assignee", "by_status"],
      "by_level":    ["EPIC", "STORY", "TASK"],
      "by_moscow":   ["MUST", "SHOULD", "COULD", "WONT"],
      "by_assignee": ["AGENT", "HUMAN"],
      "by_status":   ["PROPOSED", "APPROVED", "IN_PROGRESS", "DEFERRED", "WONT_DO", "REJECTED", "DONE"]
    },

    "severity_ladder": {
      "_comment": "§Severity (security & performance scanners). 5-level ordered ladder from most-severe to least-severe. Used by security + performance scanners; other scanners may use a subset.",
      "ordered_high_to_low": ["critical", "high", "medium", "low", "info"],
      "examples": {
        "critical": {"security": "RCE, exposed secret, auth bypass",   "performance": "Outage; > 10× regression on hot path"},
        "high":     {"security": "Exploitable with assumptions",       "performance": "> 2× regression on hot path"},
        "medium":   {"security": "Plausible attack chain",             "performance": "25–100% regression on hot path"},
        "low":      {"security": "Defense-in-depth",                   "performance": "< 25% regression on hot path"},
        "info":     {"security": "Observation; not a defect",          "performance": "Profiling note"}
      }
    },

    "perf_thresholds": {
      "_comment": "§Hot path and §Large bundle. Numeric thresholds defining the 'hot path' and 'large bundle' scanner triggers. Values drive the performance scanner's heuristics.",
      "hot_path": {
        "loop_iters_per_request":    1000,
        "wall_time_pct_attribution": 5
      },
      "large_bundle": {
        "gzipped_kb_per_chunk":        250,
        "uncompressed_mb_total_entry": 1
      }
    },

    "sort_order": {
      "_comment": "§Sort Order (canonical). 4-key sort applied recursively at every level of the hierarchy. Items are written on disk in sorted pre-order — readers never re-sort. Cross-artifact ordering invariant: index.json, daily .md, and mirror .json must have IDENTICAL orderings.",
      "keys_in_order": ["reported_date", "assignee", "moscow", "id"],
      "directions": {
        "reported_date": "ASC (oldest first)",
        "assignee":      "ASC (AGENT before HUMAN)",
        "moscow":        "priority (MUST > SHOULD > COULD > WONT)",
        "id":            "ASC (stable tiebreaker)"
      }
    },

    "fivew_oneh_twoc_fivem": {
      "_comment": "§5W1H2C5M. Every task populates every field with grounded, finding-specific analysis. Stories and epics summarize from their tasks. FORBIDDEN filler patterns (each a hard violation) are preserved in AUDIT.md prose — this block captures only the sub-block roster.",
      "5W": ["What", "Why", "Who", "When", "Where"],
      "1H": ["How"],
      "2C": ["Cost", "Constraints"],
      "5M": ["Man", "Machine", "Material", "Method", "Measurement"],
      "semantics": {
        "How":          "proposed implementation approach",
        "Cost":         "effort hours, risk level, blast radius",
        "Constraints":  "what cannot change; deps; deadlines; back-compat requirements",
        "Man":          "people / skills / reviewers",
        "Machine":      "infra / runtime / tooling",
        "Material":     "libs / data / configs",
        "Method":       "pattern / algorithm chosen",
        "Measurement":  "concrete success metric"
      }
    },

    "bootstrap_readme_sections": {
      "_comment": "§Bootstrap README. Ordered spec for `.audit/README.md` (the human-facing guide emitted on bootstrap and regenerated when missing). This block captures the ORDERED section roster + regeneration rules. The README's literal text is templated from `templates/CHEAT-SHEET.md.tmpl` and `templates/TROUBLESHOOTING.md.tmpl` for §7 and §8; sections 1-6 and 9 are prose derived from this spec. D04 extracted (2026-04-21) from AUDIT.md §Bootstrap README.",
      "sections": [
        {
          "ordinal": 1,
          "name": "Title + orientation paragraph",
          "required_content": "# Audit System heading; one-paragraph orientation stating (a) the directory is agent-managed, (b) daily scans land in reports/<date>.md, (c) nothing else in the repo is modified without explicit approval."
        },
        {
          "ordinal": 2,
          "name": "The loop (ASCII diagram)",
          "required_content": "SCAN → PROPOSED → APPROVED → IN_PROGRESS → DONE main path; DEFERRED and REJECTED branches; terminal WONT_DO. Sourced from SCHEMA.json § status_state_machine."
        },
        {
          "ordinal": 3,
          "name": "Daily 3-step",
          "required_content": "Open today's report; edit `status:` to APPROVED / WONT_DO / DEFERRED; run execute mode."
        },
        {
          "ordinal": 4,
          "name": "Where to find what",
          "required_content": "Table mapping paths to purpose: `reports/<YYYY>/<MM>/<YYYY-MM-DD>.{md,json}`, `state/{index,wont-do,in-flight}.json`, `changelog/{CHANGELOG.md,transitions.jsonl}`, `implementations/<epic>/<story>/<task>/`."
        },
        {
          "ordinal": 5,
          "name": "Status reference",
          "required_content": "The 7 status values from SCHEMA.json § status_state_machine.statuses, each with a one-line meaning.",
          "source_block": "status_state_machine.statuses"
        },
        {
          "ordinal": 6,
          "name": "MoSCoW reference",
          "required_content": "The 4 priority levels from SCHEMA.json § moscow_priorities.levels with one-line meanings.",
          "source_block": "moscow_priorities.levels"
        },
        {
          "ordinal": 7,
          "name": "Cheat sheet",
          "required_content": "Verbatim contents of `templates/CHEAT-SHEET.md.tmpl` under a `## Cheat sheet` heading.",
          "template_source": "templates/CHEAT-SHEET.md.tmpl"
        },
        {
          "ordinal": 8,
          "name": "Troubleshooting",
          "required_content": "Verbatim contents of `templates/TROUBLESHOOTING.md.tmpl` under a `## Troubleshooting` heading.",
          "template_source": "templates/TROUBLESHOOTING.md.tmpl"
        },
        {
          "ordinal": 9,
          "name": "Footer",
          "required_content": "Auto-generated disclaimer; `Last regenerated: <ISO> by <run_id>`; `AUDIT.md schema_version: <value>`."
        }
      ],
      "regeneration_rules": {
        "on_bootstrap": "Always write. Step 0 emits `.audit/README.md` as part of the scaffold.",
        "on_scan_if_missing": "Regenerate silently in Step 2 and log `readme_regenerated` note in the Run Log.",
        "never_overwrite_existing": "A normal scan MUST NOT overwrite an existing README. Forced refresh requires `MODE=consolidate`.",
        "log_event_name": "readme_regenerated"
      },
      "expected_section_count": 9
    }
  }
}
